nautobot_cdn_models/__init__.py
nautobot_cdn_models/api/__init__.py
nautobot_cdn_models/api/serializers.py
nautobot_cdn_models/api/urls.py
nautobot_cdn_models/api/views.py
nautobot_cdn_models/app-config-schema.json
nautobot_cdn_models/datasources.py
nautobot_cdn_models/filters.py
nautobot_cdn_models/forms.py
nautobot_cdn_models/graphql/__init__.py
nautobot_cdn_models/graphql/types.py
nautobot_cdn_models/homepage.py
nautobot_cdn_models/jobs/CheckBGPCommunities.py
nautobot_cdn_models/jobs/__init__.py
nautobot_cdn_models/jobs/bulk_hpc_add.py
nautobot_cdn_models/jobs/deploy_update_site_button.py
nautobot_cdn_models/jobs/node_lcdn_update_button.py
nautobot_cdn_models/migrations/0001_cdn_models.py
nautobot_cdn_models/migrations/__init__.py
nautobot_cdn_models/models/__init__.py
nautobot_cdn_models/models/contexts.py
nautobot_cdn_models/models/sites.py
nautobot_cdn_models/navigation.py
nautobot_cdn_models/querysets.py
nautobot_cdn_models/signals.py
nautobot_cdn_models/tables.py
nautobot_cdn_models/template_content.py
nautobot_cdn_models/templates/nautobot_cdn_models/cdnconfigcontext.html
nautobot_cdn_models/templates/nautobot_cdn_models/cdnconfigcontext_edit.html
nautobot_cdn_models/templates/nautobot_cdn_models/cdnconfigcontextschema.html
nautobot_cdn_models/templates/nautobot_cdn_models/cdnconfigcontextschema_edit.html
nautobot_cdn_models/templates/nautobot_cdn_models/cdnconfigcontextschema_validation.html
nautobot_cdn_models/templates/nautobot_cdn_models/cdnsite.html
nautobot_cdn_models/templates/nautobot_cdn_models/cdnsite_edit.html
nautobot_cdn_models/templates/nautobot_cdn_models/customized_jobresult.html
nautobot_cdn_models/templates/nautobot_cdn_models/hypercachememoryprofile_retrieve.html
nautobot_cdn_models/templates/nautobot_cdn_models/inc/bgp_check_results.html
nautobot_cdn_models/templates/nautobot_cdn_models/inc/device_cdn_site_tab.html
nautobot_cdn_models/templates/nautobot_cdn_models/inc/paginator.html
nautobot_cdn_models-1.1.dist-info/LICENSE
nautobot_cdn_models-1.1.dist-info/METADATA
nautobot_cdn_models-1.1.dist-info/WHEEL
nautobot_cdn_models-1.1.dist-info/RECORD
