Metadata-Version: 2.3
Name: nautobot-cdn-models
Version: 1.1
Summary: Nautobot app to model cdn objects.
License: Apache-2.0
Keywords: nautobot,nautobot-app,nautobot-plugin
Author: Network to Code, LLC
Author-email: opensource@networktocode.com
Requires-Python: >=3.8,<3.13
Classifier: Development Status :: 5 - Production/Stable
Classifier: Intended Audience :: Developers
Classifier: License :: OSI Approved :: Apache Software License
Classifier: Programming Language :: Python :: 3
Classifier: Programming Language :: Python :: 3.8
Classifier: Programming Language :: Python :: 3.9
Classifier: Programming Language :: Python :: 3.10
Classifier: Programming Language :: Python :: 3.11
Classifier: Programming Language :: Python :: 3.12
Provides-Extra: all
Requires-Dist: nautobot (>=2.0.0,<3.0.0)
Requires-Dist: netutils (>=1.0.0,<2.0.0)
Project-URL: Documentation, https://docs.nautobot.com/projects/cdn-models/en/latest/
Project-URL: Homepage, https://github.com/byrn-baker/nautobot-app-cdn-models
Project-URL: Repository, https://github.com/byrn-baker/nautobot-app-cdn-models
